aplicacion_ventas/__init__.py
aplicacion_ventas/descuentos.py
aplicacion_ventas/exceptions.py
aplicacion_ventas/gestor_ventas.py
aplicacion_ventas/impuestos.py
aplicacion_ventas/precios.py
prprogventas1-0.0.1.dist-info/licenses/LICENCE
tests/__init__.py
tests/test_app_ventas.py
prprogventas1-0.0.1.dist-info/METADATA
prprogventas1-0.0.1.dist-info/WHEEL
prprogventas1-0.0.1.dist-info/top_level.txt
prprogventas1-0.0.1.dist-info/RECORD
