Metadata-Version: 2.4
Name: prprogVentas1
Version: 0.0.1
Summary: Paquete para gestionar ventas, precios, impuestos y descuentos
Home-page: https://github.com/yatoriZ/prprogVentas1
Author: Jorddy Antonio cabana Rojas
Author-email: jorddy.crojas@gmail.com
Classifier: Programming Language :: Python :: 3
Classifier: License :: OSI Approved :: MIT License
Classifier: Operating System :: OS Independent
Requires-Python: >=3.7
License-File: LICENCE
Dynamic: author
Dynamic: author-email
Dynamic: classifier
Dynamic: description
Dynamic: description-content-type
Dynamic: home-page
Dynamic: license-file
Dynamic: requires-python
Dynamic: summary
